<?xml version="1.0" encoding="UTF-8"?>
<ti:app xmlns:ti="http://ti.appcelerator.org">
<id>net.robertcarlsen.MobileLogger</id>
<name>MobileLogger</name>
<version>1.2.2</version>
<publisher>Robert Carlsen</publisher>
<url>http://robertcarlsen.net</url>
<description>Log location, heading, speed, altitude, accelerometer, sound level, trip duration and distance.</description>
<copyright>2010 by Robert Carlsen</copyright>
<icon>Icon.png</icon>
    <persistent-wifi>false</persistent-wifi>
    <prerendered-icon>false</prerendered-icon>
    <statusbar-style>default</statusbar-style>
    <statusbar-hidden>false</statusbar-hidden>
    <analytics>false</analytics>
<guid>85e942c2-cae5-48e1-8f05-d32621ee71bf</guid>
</ti:app>
